better_json_tools/__init__.py
better_json_tools/compact_encoder.py
better_json_tools/json_walker.py
better_json_tools/jsonc.py
better_json_tools/py.typed
better_json_tools-1.0.4.dist-info/LICENSE
better_json_tools-1.0.4.dist-info/METADATA
better_json_tools-1.0.4.dist-info/WHEEL
better_json_tools-1.0.4.dist-info/top_level.txt
better_json_tools-1.0.4.dist-info/RECORD
