Metadata-Version: 2.1
Name: better-json-tools
Version: 1.0.4
Summary: Python module that adds tools to make working with JSON data easier.
Author: Nusiq
License: MIT
Project-URL: Source, https://github.com/Nusiq/better_json_tools/tree/master
Project-URL: Documentation, https://better-json-tools.readthedocs.io/en/stable/
Classifier: Development Status :: 5 - Production/Stable
Classifier: License :: OSI Approved :: MIT License
Classifier: Programming Language :: Python :: 3.10
Requires-Python: >=3.10
License-File: LICENSE
